pyPodcastParser/Item.py
pyPodcastParser/episode.py
pyPodcastParser/__init__.py
pyPodcastParser/Podcast.py
pyPodcastParser-2.0.0.dist-info/RECORD
pyPodcastParser-2.0.0.dist-info/top_level.txt
pyPodcastParser-2.0.0.dist-info/metadata.json
pyPodcastParser-2.0.0.dist-info/WHEEL
pyPodcastParser-2.0.0.dist-info/DESCRIPTION.rst
pyPodcastParser-2.0.0.dist-info/METADATA
