Metadata-Version: 2.0
Name: pyPodcastParser
Version: 2.0.0
Summary: pyPodcastParser is a podcast parser.
Home-page: https://github.com/jrigden/pyPodcastParser
Author: Jason Rigden
Author-email: jasonrigden@gmail.com
License: MIT
Keywords: podcast,parser,rss,feed
Platform: UNKNOWN
Classifier: Development Status :: 5 - Production/Stable
Classifier: Intended Audience :: Developers
Classifier: Topic :: Software Development :: Libraries :: Python Modules
Classifier: Topic :: Text Processing :: Markup :: XML
Classifier: License :: OSI Approved :: MIT License
Classifier: Programming Language :: Python :: 2
Classifier: Programming Language :: Python :: 2.6
Classifier: Programming Language :: Python :: 2.7
Classifier: Programming Language :: Python :: 3
Classifier: Programming Language :: Python :: 3.2
Classifier: Programming Language :: Python :: 3.3
Classifier: Programming Language :: Python :: 3.4
Classifier: Programming Language :: Python :: 3.5
Requires-Dist: beautifulsoup4
